autodidaqt_common/__init__.py
autodidaqt_common/collation.py
autodidaqt_common/enum.py
autodidaqt_common/json.py
autodidaqt_common/path.py
autodidaqt_common/remote/__init__.py
autodidaqt_common/remote/command.py
autodidaqt_common/remote/config.py
autodidaqt_common/remote/middleware.py
autodidaqt_common/remote/schema.py
autodidaqt_common/remote/socket.py
autodidaqt_common/remote/utils.py
autodidaqt_common/schema.py
autodidaqt_common-0.1.0.dist-info/LICENSE.txt
autodidaqt_common-0.1.0.dist-info/WHEEL
autodidaqt_common-0.1.0.dist-info/METADATA
autodidaqt_common-0.1.0.dist-info/RECORD
