Metadata-Version: 2.1
Name: autodidaqt-common
Version: 0.1.0
Summary: Common code for autodiDAQt and autodiDAQt-receiver.
Home-page: https://github.com/chstan/autodidaqt-common
License: GNU GPL v3.0
Keywords: data acquisition,physics,instrumentation,DAQ
Author: chstan
Author-email: chstansbury@gmail.com
Requires-Python: >=3.8,<3.10
Classifier: Intended Audience :: Developers
Classifier: Intended Audience :: Science/Research
Classifier: License :: OSI Approved :: GNU General Public License v3 or later (GPLv3+)
Classifier: License :: Other/Proprietary License
Classifier: Natural Language :: English
Classifier: Operating System :: OS Independent
Classifier: Programming Language :: Python :: 3
Classifier: Programming Language :: Python :: 3.8
Classifier: Programming Language :: Python :: 3.9
Classifier: Topic :: Scientific/Engineering
Classifier: Topic :: Scientific/Engineering :: Physics
Classifier: Topic :: Software Development :: Libraries :: Python Modules
Requires-Dist: dataclasses_json (>=0.5.0,<0.6.0)
Requires-Dist: loguru (>=0.3.2,<0.4.0)
Requires-Dist: numpy (>=1.20,<2.0)
Requires-Dist: pynng (>=0.7.1,<0.8.0)
Requires-Dist: xarray (>=0.18.2)
Project-URL: Repository, https://github.com/chstan/autodidaqt-common
